source_gridly/__init__.py
source_gridly/helpers.py
source_gridly/run.py
source_gridly/source.py
source_gridly/spec.yaml
airbyte_source_gridly-0.1.40.dist-info/METADATA
airbyte_source_gridly-0.1.40.dist-info/WHEEL
airbyte_source_gridly-0.1.40.dist-info/entry_points.txt
airbyte_source_gridly-0.1.40.dist-info/RECORD
